company_pinax_stripe-4.4.1.dist-info/METADATA
company_pinax_stripe-4.4.1.dist-info/RECORD
company_pinax_stripe-4.4.1.dist-info/WHEEL
company_pinax_stripe-4.4.1.dist-info/top_level.txt
pinax/__init__.py
pinax/stripe/__init__.py
pinax/stripe/admin.py
pinax/stripe/apps.py
pinax/stripe/conf.py
pinax/stripe/forms.py
pinax/stripe/hooks.py
pinax/stripe/managers.py
pinax/stripe/middleware.py
pinax/stripe/mixins.py
pinax/stripe/models.py
pinax/stripe/signals.py
pinax/stripe/urls.py
pinax/stripe/utils.py
pinax/stripe/views.py
pinax/stripe/webhooks.py
pinax/stripe/actions/__init__.py
pinax/stripe/actions/accounts.py
pinax/stripe/actions/charges.py
pinax/stripe/actions/coupons.py
pinax/stripe/actions/customers.py
pinax/stripe/actions/events.py
pinax/stripe/actions/exceptions.py
pinax/stripe/actions/externalaccounts.py
pinax/stripe/actions/invoices.py
pinax/stripe/actions/plans.py
pinax/stripe/actions/refunds.py
pinax/stripe/actions/sources.py
pinax/stripe/actions/subscriptions.py
pinax/stripe/actions/transfers.py
pinax/stripe/management/__init__.py
pinax/stripe/management/commands/__init__.py
pinax/stripe/management/commands/init_customers.py
pinax/stripe/management/commands/sync_coupons.py
pinax/stripe/management/commands/sync_customers.py
pinax/stripe/management/commands/sync_plans.py
pinax/stripe/management/commands/update_charge_availability.py
pinax/stripe/migrations/0001_initial.py
pinax/stripe/migrations/0002_auto_20151205_1451.py
pinax/stripe/migrations/0003_make_cvc_check_blankable.py
pinax/stripe/migrations/0004_plan_metadata.py
pinax/stripe/migrations/0005_auto_20161006_1445.py
pinax/stripe/migrations/0006_coupon.py
pinax/stripe/migrations/0007_auto_20170108_1202.py
pinax/stripe/migrations/0008_auto_20170509_1736.py
pinax/stripe/migrations/0009_auto_20170825_1841.py
pinax/stripe/migrations/0010_connect.py
pinax/stripe/migrations/0011_auto_20171121_1648.py
pinax/stripe/migrations/0011_auto_20171123_2016.py
pinax/stripe/migrations/0013_charge_outcome.py
pinax/stripe/migrations/0014_auto_20180413_1959.py
pinax/stripe/migrations/0014_blank_with_null.py
