Metadata-Version: 2.1
Name: company-pinax-stripe
Version: 4.4.1
Summary: a payments Django app for Stripe for companies
Home-page: https://github.com/JamesJGarner/company-pinax-stripe
Author: MCNA
Author-email: developers@mycompanyneedsa.co
License: MIT
Platform: UNKNOWN
Classifier: Development Status :: 5 - Production/Stable
Classifier: Environment :: Web Environment
Classifier: Intended Audience :: Developers
Classifier: License :: OSI Approved :: BSD License
Classifier: Operating System :: OS Independent
Classifier: Programming Language :: Python
Classifier: Programming Language :: Python :: 2
Classifier: Programming Language :: Python :: 3
Classifier: Framework :: Django
Provides-Extra: testing
Requires-Dist: django-appconf (>=1.0.1)
Requires-Dist: jsonfield (>=1.0.3)
Requires-Dist: stripe (>=2.0)
Requires-Dist: django (>=1.8)
Requires-Dist: pytz
Requires-Dist: six
Requires-Dist: django-ipware (==2.1.0)
Provides-Extra: testing
Requires-Dist: mock; extra == 'testing'
Requires-Dist: pytest; extra == 'testing'
Requires-Dist: pytest-django; extra == 'testing'
